{"type":"FeatureCollection", "features": [
{"type":"Feature","geometry":{"type":"Point","coordinates":[117.07058591907992,32.167062386691384,-1.7976931348623157e+308]},"properties":{"id":"29","name":"实践家文教基金会","shopowner":"刘明","telephone":"18110924766","theme":"农场(亲子游)","x":117.070585919,"y":32.1670623867,"type":"农场(亲子游)","ORIG_FID":0}},
{"type":"Feature","geometry":{"type":"Point","coordinates":[117.0689824362156,32.16483203671925,-1.7976931348623157e+308]},"properties":{"id":"50","name":"中草药园","shopowner":"","telephone":"","theme":"农场","x":117.068982436,"y":32.1648320367,"type":"农场","ORIG_FID":1}},
{"type":"Feature","geometry":{"type":"Point","coordinates":[117.0692402872968,32.16373763378613,-1.7976931348623157e+308]},"properties":{"id":"533","name":"行知田园","shopowner":"","telephone":"","theme":"农场","x":117.069240287,"y":32.1637376338,"type":"农场","ORIG_FID":2}},
{"type":"Feature","geometry":{"type":"Point","coordinates":[117.06869563149723,32.15905123873637,-1.7976931348623157e+308]},"properties":{"id":"536","name":"壹畦趣草莓园","shopowner":"","telephone":"","theme":"农场","x":117.069052665,"y":32.1588270027,"type":"农场","ORIG_FID":3}},
{"type":"Feature","geometry":{"type":"Point","coordinates":[117.07248218358814,32.161606222821376,-1.7976931348623157e+308]},"properties":{"id":"26","name":"荣强蓝莓","shopowner":"蒋利民","telephone":"15395502701","theme":"农场","x":117.072482184,"y":32.1616062228,"type":"农场","ORIG_FID":4}},
{"type":"Feature","geometry":{"type":"Point","coordinates":[117.07409467314255,32.16822325427296,-1.7976931348623157e+308]},"properties":{"id":"28","name":"行走的树","shopowner":"田家友","telephone":"13866667830","theme":"景点","x":117.073551769,"y":32.1682901011,"type":"景点","ORIG_FID":5}},
{"type":"Feature","geometry":{"type":"Point","coordinates":[117.07201140717928,32.16488670631628,-1.7976931348623157e+308]},"properties":{"id":"995","name":"情圆农场","shopowner":"","telephone":"","theme":"农场","x":117.072011407,"y":32.1648867063,"type":"农场","ORIG_FID":6}},
{"type":"Feature","geometry":{"type":"Point","coordinates":[117.06689829209938,32.16560439911848,-1.7976931348623157e+308]},"properties":{"id":"17","name":"小李瓜园","shopowner":"李辉姚","telephone":"18134526448","theme":"农场","x":117.066898292,"y":32.1656043991,"type":"农场","ORIG_FID":7}},
{"type":"Feature","geometry":{"type":"Point","coordinates":[117.06336960115277,32.16141353969658,-1.7976931348623157e+308]},"properties":{"id":"18","name":"红果参","shopowner":"郑···","telephone":"","theme":"农场(饮品原料生产基地)","x":117.063373306,"y":32.1613914242,"type":"农场(饮品原料生产基地)","ORIG_FID":8}},
{"type":"Feature","geometry":{"type":"Point","coordinates":[117.06964870155537,32.162614992506064,-1.7976931348623157e+308]},"properties":{"id":"991","name":"暂无信息","shopowner":"","telephone":"","theme":"","x":117.069648702,"y":32.1626149925,"type":"","ORIG_FID":9}},
{"type":"Feature","geometry":{"type":"Point","coordinates":[117.05896638806519,32.159581207610586,-1.7976931348623157e+308]},"properties":{"id":"20","name":"马郢农场","shopowner":"梅忠","telephone":"18955146271","theme":"农场(虾稻种植)","x":117.058966388,"y":32.1595812076,"type":"农场(虾稻种植)","ORIG_FID":10}}
]}